{
    "content" : {

        "global" : [

            {
                "id" : "type-customer",
                "type" : "radio",
                "text" : "Asiakas"
            },

            {
                "id" : "type-selection",
                "type" : "radio",
                "text" : "Myynti"
            },

            {
                "id" : "type-selection",
                "type" : "radio",
                "text" : "Kontakti"
            },

            {
                "id" : "type-selection",
                "type" : "radio",
                "text" : "Tapaaminen"
            },

            {
                "id" : ""
            }

        ],

        "addCustomer" : [

            {
                "id" : "input-name",
                "type" : "input"
            }

        ]

    }
}